{
  "parent": "minecraft:recipes/root",
  "criteria": {
    "has_raw_zinc": {
      "conditions": {
        "items": [
          {
            "items": [
              "mysticalsteamage:raw_zinc"
            ]
          }
        ]
      },
      "trigger": "minecraft:inventory_changed"
    },
    "has_the_recipe": {
      "conditions": {
        "recipe": "mysticalsteamage:zinc_ingot_2"
      },
      "trigger": "minecraft:recipe_unlocked"
    }
  },
  "requirements": [
    [
      "has_raw_zinc",
      "has_the_recipe"
    ]
  ],
  "rewards": {
    "recipes": [
      "mysticalsteamage:zinc_ingot_2"
    ]
  },
  "sends_telemetry_event": false
}